[
  {
    "id": "1778537568895",
    "userId": "1777845639356",
    "type": "Walking",
    "duration": "50",
    "date": "2026-05-11",
    "calories": 131,
    "notes": ""
  },
  {
    "id": "1778363212294",
    "userId": "1778276463231",
    "type": "Weight training",
    "duration": "60",
    "date": "2026-05-09",
    "calories": 275,
    "notes": ""
  },
  {
    "id": "1778361770231",
    "userId": "1777503137317",
    "type": "Running",
    "duration": "20",
    "date": "2026-05-09",
    "calories": 173,
    "notes": ""
  },
  {
    "id": "1778355489790",
    "userId": "1777845639356",
    "type": "Yoga",
    "duration": "45",
    "date": "2026-05-09",
    "calories": "300",
    "notes": ""
  },
  {
    "id": "1778295090547",
    "userId": "1777845639356",
    "type": "Cycling",
    "duration": "50",
    "date": "2026-05-09",
    "calories": "500",
    "notes": ""
  },
  {
    "id": "1778295055069",
    "userId": "1777845639356",
    "type": "Swimming",
    "duration": "30",
    "date": "2026-05-09",
    "calories": "400",
    "notes": ""
  },
  {
    "id": "1778292875648",
    "userId": "1777503137317",
    "type": "Weight training",
    "duration": "20",
    "date": "2026-05-09",
    "calories": "400",
    "notes": ""
  },
  {
    "id": "1778291379248",
    "userId": "1777503137317",
    "type": "Walking",
    "duration": "45",
    "date": "2026-05-09",
    "calories": "300",
    "notes": ""
  },
  {
    "id": "act_r_08",
    "userId": "1777845639356",
    "type": "Running",
    "duration": "65",
    "date": "2026-05-08",
    "calories": "350",
    "notes": ""
  },
  {
    "id": "act_r_07",
    "userId": "1777845639356",
    "type": "Cycling",
    "duration": "70",
    "date": "2026-05-07",
    "calories": "400",
    "notes": ""
  }
]